assort/__init__.py
assort/core.py
assort-0.2.1.dist-info/METADATA
assort-0.2.1.dist-info/WHEEL
assort-0.2.1.dist-info/top_level.txt
assort-0.2.1.dist-info/RECORD
