Metadata-Version: 2.4
Name: assort
Version: 0.2.1
Summary: Using AI to sort lists of unstructured text through iterative batches.
Author-email: Tom Gorbett <wthomasgorbett@gmail.com>
License: MIT
Classifier: Development Status :: 2 - Pre-Alpha
Classifier: Programming Language :: Python :: 3
Classifier: License :: OSI Approved :: MIT License
Classifier: Operating System :: OS Independent
Requires-Python: >=3.9
Requires-Dist: openai>=1.14.0
Requires-Dist: tiktoken>=0.7.0
